{
    "Weight must be integer": "Вес должен быть числом",
    "Weight": "Не более {upTo}",
    "Criteria or Goal": "Критерий или цель",
    "Add achievement criteria": "Добавить критерий",
    "Weight must be in range": "Вес критерия должен быть от 1 до {upTo}",
    "Add": "Добавить",
    "Save": "Сохранить",
    "Title must be unique": "Критерий должен быть уникальным",
    "Enter goal name": "Введите название цели",
    "Enter criteria": "Укажите критерий",
    "Search by goals": "Поиск по целям"
}
